setup.py
awsclpy/__init__.py
awsclpy/awsclpy.py
awsclpy/utils.py
awsclpy.egg-info/PKG-INFO
awsclpy.egg-info/SOURCES.txt
awsclpy.egg-info/dependency_links.txt
awsclpy.egg-info/not-zip-safe
awsclpy.egg-info/requires.txt
awsclpy.egg-info/top_level.txt