Metadata-Version: 1.1
Name: awsclpy
Version: 0.3.5
Summary: Chain AWSCLI commands in Python.
Home-page: http://github.com/hamidnazari/awsclpy
Author: Hamid Nazari
Author-email: hn@linux.com
License: MIT
Keywords: awsclpy,awscli,aws,amazon web services,command line interface
Platform: UNKNOWN
Classifier: Programming Language :: Python
Classifier: Programming Language :: Python :: 2.6
Classifier: Programming Language :: Python :: 2.7
Classifier: Intended Audience :: Developers
Classifier: License :: OSI Approved :: MIT License
Classifier: Operating System :: OS Independent
Classifier: Topic :: Software Development
Classifier: Topic :: Software Development :: Libraries
Classifier: Topic :: Software Development :: Libraries :: Python Modules
Classifier: Development Status :: 4 - Beta
